data_memory.v
// Memória de Dados
module data_memory(
    input clk,                   // Sinal de clock
    input mem_read,              // Habilita leitura da memória
    input mem_write,             // Habilita escrita na memória
    input [31:0] addr,           // Endereço de memória
    input [31:0] write_data,     // Dado a ser escrito na memória
    output [31:0] read_data      // Dado lido da memória
);
    reg [31:0] memory [0:255];   // Memória com 256 posições de 32 bits

    // Leitura da memória
    assign read_data = (mem_read) ? memory[addr[7:0]] : 0;

    // Escrita na memória (sincronizada com o clock)
    always @(posedge clk) begin
        if (mem_write) memory[addr[7:0]] <= write_data;
    end
endmodule

sign_extension.v
// Extensão de Sinal
module sign_extension(
    input [15:0] immediate,      // Entrada de 16 bits
    output [31:0] extended       // Saída de 32 bits com extensão de sinal
);
    assign extended = {{16{immediate[15]}}, immediate};
endmodule

alu_control_unit.v
// Unidade de Controle da ALU
module alu_control_unit(
    input [1:0] alu_op,           // Sinal de controle da ALU (vem da unidade de controle principal)
    input [5:0] funct,            // Campo funct da instrução (usado para instruções do tipo R)
    output reg [3:0] alu_ctrl     // Sinal de controle para a ALU
);
    always @(*) begin
        case (alu_op)
            2'b00: alu_ctrl = 4'b0010; // LW/SW: operação de ADD (soma)
            2'b01: alu_ctrl = 4'b0110; // BEQ: operação de SUB (subtração)
            2'b10: begin
                case (funct)
                    6'b100000: alu_ctrl = 4'b0010; // ADD
                    6'b100010: alu_ctrl = 4'b0110; // SUB
                    6'b100100: alu_ctrl = 4'b0000; // AND
                    6'b100101: alu_ctrl = 4'b0001; // OR
                    6'b101010: alu_ctrl = 4'b0111; // SLT
                    default: alu_ctrl = 4'b0000;   // Caso padrão
                endcase
            end
            default: alu_ctrl = 4'b0000; // Caso padrão
        endcase
    end
endmodule

alu.v
// Unidade Lógica e Aritmética (ALU)
module alu(
    input [31:0] a,              // Operando 1
    input [31:0] b,              // Operando 2
    input [3:0] alu_ctrl,        // Sinal de controle para selecionar a operação
    output reg [31:0] result,    // Resultado da operação
    output zero                  // Sinal que indica se o resultado é zero
);
    always @(*) begin
        case (alu_ctrl)
            4'b0010: result = a + b;  // Soma
            4'b0110: result = a - b;  // Subtração
            4'b0000: result = a & b;  // AND lógico
            4'b0001: result = a | b;  // OR lógico
            4'b0111: result = (a < b) ? 1 : 0; // SLT (set less than)
            default: result = 0;      // Caso padrão
        endcase
    end

    assign zero = (result == 0); // Define o sinal zero como 1 se o resultado for zero
endmodule

register_file.v
module register_file(
    input clk,
    input reset, // Adicione o sinal de reset
    input reg_write,
    input [4:0] read_reg1,
    input [4:0] read_reg2,
    input [4:0] write_reg,
    input [31:0] write_data,
    output [31:0] read_data1,
    output [31:0] read_data2
);
    reg [31:0] reg_file [0:31];

    // Inicialização dos registradores com reset
    integer i;
    always @(posedge clk or posedge reset) begin
        if (reset) begin
            for (i = 0; i < 32; i = i + 1)
                reg_file[i] <= 32'b0; // Inicializa todos os registradores com zero
        end
        else if (reg_write && write_reg != 5'b0) begin
            reg_file[write_reg] <= write_data; // Escreve no registrador
        end
    end

    assign read_data1 = reg_file[read_reg1];
    assign read_data2 = reg_file[read_reg2];
endmodule

control_unit.v
module control_unit (
    input wire [5:0] opcode,
    output reg reg_dst,
    output reg jump,
    output reg branch,
    output reg mem_read,
    output reg mem_to_reg,
    output reg mem_write,
    output reg alu_src,
    output reg reg_write,
    output reg [1:0] alu_op
);
    always @(*) begin
        case (opcode)
            6'b000000: begin // R-type
                reg_dst = 1;
                jump = 0;
                branch = 0;
                mem_read = 0;
                mem_to_reg = 0;
                mem_write = 0;
                alu_src = 0;
                reg_write = 1;
                alu_op = 2'b10;
            end
            6'b100011: begin // lw
                reg_dst = 0;
                jump = 0;
                branch = 0;
                mem_read = 1;
                mem_to_reg = 1;
                mem_write = 0;
                alu_src = 1;
                reg_write = 1;
                alu_op = 2'b00;
            end
            6'b101011: begin // sw
                reg_dst = 0;
                jump = 0;
                branch = 0;
                mem_read = 0;
                mem_to_reg = 0;
                mem_write = 1;
                alu_src = 1;
                reg_write = 0;
                alu_op = 2'b00;
            end
            6'b000100: begin // beq
                reg_dst = 0;
                jump = 0;
                branch = 1;
                mem_read = 0;
                mem_to_reg = 0;
                mem_write = 0;
                alu_src = 0;
                reg_write = 0;
                alu_op = 2'b01;
            end
            6'b000010: begin // j
                reg_dst = 0;
                jump = 1;
                branch = 0;
                mem_read = 0;
                mem_to_reg = 0;
                mem_write = 0;
                alu_src = 0;
                reg_write = 0;
                alu_op = 2'b00;
            end
            default: begin // Instruções não suportadas
                reg_dst = 0;
                jump = 0;
                branch = 0;
                mem_read = 0;
                mem_to_reg = 0;
                mem_write = 0;
                alu_src = 0;
                reg_write = 0;
                alu_op = 2'b00;
            end
        endcase
    end
endmodule

instruction_memory.v
// Memória de Instruções
module instruction_memory(
    input [31:0] addr,           // Endereço da instrução
    output [31:0] instruction    // Instrução lida
);
    reg [31:0] memory [0:255];   // Memória de instruções com 256 posições de 32 bits

    // Leitura da memória de instruções
    assign instruction = memory[addr[9:2]];
endmodule

pc.v
module pc(
    input clk,
    input reset,
    input [31:0] pc_next,
    output reg [31:0] pc
);
    always @(posedge clk or posedge reset) begin
        if (reset)
            pc <= 32'b0; // Reinicializa o PC se o reset estiver ativo
        else
            pc <= pc_next; // Atualiza o PC com o próximo valor
    end
endmodule

mips_single_cycle.v
module mips_single_cycle(
    input wire clk,
    input wire reset,
    output wire [31:0] alu_input_2,
    output wire [31:0] pc,           // PC atual
    output wire [31:0] instruction,  // Instrução atual
    output wire [31:0] reg_t0,       // Registrador $t0 (reg[8])
    output wire [31:0] reg_t1,       // Registrador $t1 (reg[9])
    output wire [31:0] reg_t2,       // Registrador $t2 (reg[10])
    output wire [31:0] reg_t3,       // Registrador $t3 (reg[11])
    output wire [31:0] mem_read_data, // Dado lido da memória
    output wire [31:0] alu_result,   // Resultado da ALU
    output wire zero                // Flag zero da ALU
);
    wire [31:0] pc_next, read_data_1, read_data_2, write_data;
    wire [31:0] sign_extend;
    wire [3:0] alu_ctrl;
    wire [1:0] alu_op;
    wire reg_dst, jump, branch, mem_read, mem_to_reg, mem_write, alu_src, reg_write;

    // Banco de registradores
    reg [31:0] reg_file [0:31];

    // Conecta os registradores às portas
    assign reg_t0 = reg_file[8];
    assign reg_t1 = reg_file[9];
    assign reg_t2 = reg_file[10];
    assign reg_t3 = reg_file[11];

    // Program Counter
  pc pc_inst (
        .clk(clk),
        .reset(reset),
        .pc_next(pc_next), 
        .pc(pc)
);
    assign pc_next = (jump) ? {pc[31:28], instruction[25:0], 2'b00} :
                     (branch & zero) ? (pc + 4 + (sign_extend << 2)) : (pc + 4);

    // Memória de Instruções
    instruction_memory IM (
        .addr(pc),
        .instruction(instruction)
);

    // Unidade de Controle
    control_unit cu_inst (
        .opcode(instruction[31:26]),
        .reg_dst(reg_dst),
        .alu_src(alu_src),
        .mem_to_reg(mem_to_reg),
        .reg_write(reg_write),
        .mem_read(mem_read),
        .mem_write(mem_write),
        .branch(branch),
        .jump(jump),
        .alu_op(alu_op)
    );

    // Banco de Registradores
    register_file rf_inst (
        .clk(clk),
        .reg_write(reg_write),
        .read_reg1(instruction[25:21]),
        .read_reg2(instruction[20:16]),
        .write_reg((reg_dst) ? instruction[15:11] : instruction[20:16]),
        .write_data(write_data),
        .read_data1(read_data_1),
        .read_data2(read_data_2)
    );

    // ALU
    alu alu_inst (
        .a(read_data_1),
        .b(alu_input_2),
        .alu_ctrl(alu_ctrl),
        .result(alu_result),
        .zero(zero)
    );

    // Unidade de Controle da ALU
    alu_control_unit alu_ctrl_inst (
        .alu_op(alu_op),
        .funct(instruction[5:0]),
        .alu_ctrl(alu_ctrl)
    );

    // Extensão de Sinal
    sign_extension se_inst (
        .immediate(instruction[15:0]),
        .extended(sign_extend)
    );

    // Memória de Dados
    data_memory dm_inst (
        .clk(clk),
        .mem_read(mem_read),
        .mem_write(mem_write),
        .addr(alu_result),
        .write_data(read_data_2),
        .read_data(mem_read_data)
    );

    assign write_data = (mem_to_reg) ? mem_read_data : alu_result;
endmodule

tb_mips_single_cycle.v
`timescale 1ns / 1ps

module tb_mips_single_cycle;
    reg clk;
    reg reset;

    // Sinais de saída do módulo mips_single_cycle
    wire [31:0] pc;
    wire [31:0] instruction;
    wire [31:0] reg_t0, reg_t1, reg_t2, reg_t3;
    wire [31:0] mem_read_data;
    wire [31:0] alu_result;
    wire zero;

    // Instância do processador
    mips_single_cycle uut (
        .clk(clk),
        .reset(reset),
        .alu_input_2(),
        .pc(pc),
        .instruction(instruction),
        .reg_t0(reg_t0),
        .reg_t1(reg_t1),
        .reg_t2(reg_t2),
        .reg_t3(reg_t3),
        .mem_read_data(mem_read_data),
        .alu_result(alu_result),
        .zero(zero)
    );

    // Geração do clock
    always #5 clk = ~clk;

    // Inicialização e monitoramento
    initial begin
        // Inicializa arquivo de onda (se necessário)
        $dumpfile("waveform.vcd");
        $dumpvars(0, tb_mips_single_cycle);

        // Inicializa clock e reset
        clk = 0;
        reset = 1;

        // Carrega as instruções na memória
        uut.IM.memory[0] = 32'h20090005; // addi $t1, $zero, 5
        uut.IM.memory[1] = 32'h200A000A; // addi $t2, $zero, 10
        uut.IM.memory[2] = 32'h012A4020; // add $t0, $t1, $t2
        uut.IM.memory[3] = 32'h012A4022; // sub $t0, $t1, $t2
        uut.IM.memory[4] = 32'h012A4024; // and $t0, $t1, $t2
        uut.IM.memory[5] = 32'h012A4025; // or $t0, $t1, $t2
        uut.IM.memory[6] = 32'hAC0A0000; // sw $t2, 0($zero)
        uut.IM.memory[7] = 32'h8C0B0000; // lw $t3, 0($zero)
        uut.IM.memory[8] = 32'h11690002; // beq $t3, $t1, próximo
        uut.IM.memory[9] = 32'h08000000; // j 0 (loop infinito)

        // Mensagem inicial
        $display("================================================");
        $display("Iniciando simulação do MIPS single-cycle");
        $display("================================================");

        // Desativa reset após 10 ns
        #10 reset = 0;
        $display("[Tempo %0t] Reset desativado.", $time);

        // Configura o $monitor para acompanhar mudanças nos sinais principais
        $monitor("[Tempo %0t] PC = 0x%h | Instrução = 0x%h | $t0 = 0x%h | $t1 = 0x%h | $t2 = 0x%h | $t3 = 0x%h | ALU Result = 0x%h | Zero = %b | Mem Read Data = 0x%h",
                 $time, pc, instruction, reg_t0, reg_t1, reg_t2, reg_t3, alu_result, zero, mem_read_data);

        // Executa por 200 ns
        #200;

        // Exibe resultados finais
        $display("\n================================================");
        $display("Resultados finais:");
        $display("================================================");
        $display("PC final: 0x%h", pc);
        $display("Conteúdo de registradores:");
        $display("  - Registrador \$t0 (reg[8]) = 0x%h", reg_t0);
        $display("  - Registrador \$t1 (reg[9]) = 0x%h", reg_t1);
        $display("  - Registrador \$t2 (reg[10]) = 0x%h", reg_t2);
        $display("  - Registrador \$t3 (reg[11]) = 0x%h", reg_t3);
        $display("Resultado final da ALU: 0x%h", alu_result);
        $display("Flag Zero: %b", zero);
        $display("Dado lido da memória: 0x%h", mem_read_data);
        $display("================================================");

        // Finaliza a simulação
        $finish;
    end
endmodule

waveform.vcd
$date
	Sun Feb 16 18:24:42 2025
$end
$version
	Icarus Verilog
$end
$timescale
	1ps
$end
$scope module tb_mips_single_cycle $end
$var wire 1 ! zero $end
$var wire 32 " reg_t3 [31:0] $end
$var wire 32 # reg_t2 [31:0] $end
$var wire 32 $ reg_t1 [31:0] $end
$var wire 32 % reg_t0 [31:0] $end
$var wire 32 & pc [31:0] $end
$var wire 32 ' mem_read_data [31:0] $end
$var wire 32 ( instruction [31:0] $end
$var wire 32 ) alu_result [31:0] $end
$var reg 1 * clk $end
$var reg 1 + reset $end
$scope module uut $end
$var wire 32 , alu_input_2 [31:0] $end
$var wire 1 * clk $end
$var wire 32 - reg_t0 [31:0] $end
$var wire 32 . reg_t1 [31:0] $end
$var wire 32 / reg_t2 [31:0] $end
$var wire 32 0 reg_t3 [31:0] $end
$var wire 1 + reset $end
$var wire 1 ! zero $end
$var wire 32 1 write_data [31:0] $end
$var wire 32 2 sign_extend [31:0] $end
$var wire 1 3 reg_write $end
$var wire 1 4 reg_dst $end
$var wire 32 5 read_data_2 [31:0] $end
$var wire 32 6 read_data_1 [31:0] $end
$var wire 32 7 pc_next [31:0] $end
$var wire 32 8 pc [31:0] $end
$var wire 1 9 mem_write $end
$var wire 1 : mem_to_reg $end
$var wire 32 ; mem_read_data [31:0] $end
$var wire 1 < mem_read $end
$var wire 1 = jump $end
$var wire 32 > instruction [31:0] $end
$var wire 1 ? branch $end
$var wire 1 @ alu_src $end
$var wire 32 A alu_result [31:0] $end
$var wire 2 B alu_op [1:0] $end
$var wire 4 C alu_ctrl [3:0] $end
$scope module IM $end
$var wire 32 D instruction [31:0] $end
$var wire 32 E addr [31:0] $end
$upscope $end
$scope module alu_ctrl_inst $end
$var wire 6 F funct [5:0] $end
$var wire 2 G alu_op [1:0] $end
$var reg 4 H alu_ctrl [3:0] $end
$upscope $end
$scope module alu_inst $end
$var wire 4 I alu_ctrl [3:0] $end
$var wire 32 J b [31:0] $end
$var wire 1 ! zero $end
$var wire 32 K a [31:0] $end
$var reg 32 L result [31:0] $end
$upscope $end
$scope module cu_inst $end
$var wire 6 M opcode [5:0] $end
$var reg 2 N alu_op [1:0] $end
$var reg 1 @ alu_src $end
$var reg 1 ? branch $end
$var reg 1 = jump $end
$var reg 1 < mem_read $end
$var reg 1 : mem_to_reg $end
$var reg 1 9 mem_write $end
$var reg 1 4 reg_dst $end
$var reg 1 3 reg_write $end
$upscope $end
$scope module dm_inst $end
$var wire 32 O addr [31:0] $end
$var wire 1 * clk $end
$var wire 1 < mem_read $end
$var wire 1 9 mem_write $end
$var wire 32 P write_data [31:0] $end
$var wire 32 Q read_data [31:0] $end
$upscope $end
$scope module pc_inst $end
$var wire 1 * clk $end
$var wire 32 R pc_next [31:0] $end
$var wire 1 + reset $end
$var reg 32 S pc [31:0] $end
$upscope $end
$scope module rf_inst $end
$var wire 1 * clk $end
$var wire 32 T read_data1 [31:0] $end
$var wire 32 U read_data2 [31:0] $end
$var wire 5 V read_reg1 [4:0] $end
$var wire 5 W read_reg2 [4:0] $end
$var wire 1 3 reg_write $end
$var wire 1 X reset $end
$var wire 32 Y write_data [31:0] $end
$var wire 5 Z write_reg [4:0] $end
$var integer 32 [ i [31:0] $end
$upscope $end
$scope module se_inst $end
$var wire 16 \ immediate [15:0] $end
$var wire 32 ] extended [31:0] $end
$upscope $end
$upscope $end
$upscope $end
$enddefinitions $end
$comment Show the parameter values. $end
$dumpall
$end
#0
$dumpvars
b101 ]
b101 \
bx [
b1001 Z
bx Y
zX
b1001 W
b0 V
bx U
bx T
b0 S
b100 R
b0 Q
bx P
bx O
b0 N
b1000 M
bx L
bx K
bz J
b10 I
b10 H
b0 G
b101 F
b0 E
b100000000010010000000000000101 D
b10 C
b0 B
bx A
1@
0?
b100000000010010000000000000101 >
0=
0<
b0 ;
0:
09
b0 8
b100 7
bx 6
bx 5
04
13
b101 2
bx 1
bx 0
bx /
bx .
bx -
bz ,
1+
0*
bx )
b100000000010010000000000000101 (
b0 '
b0 &
bx %
bx $
bx #
bx "
x!
$end
#5000
1*
#10000
0*
0+
#15000
b1010 Z
b1010 2
b1010 ]
b1010 \
b1010 F
b1010 W
b1000 7
b1000 R
b100000000010100000000000001010 (
b100000000010100000000000001010 >
b100000000010100000000000001010 D
b100 &
b100 8
b100 E
b100 S
1*
#20000
0*
#25000
b1000 Z
b10 B
b10 G
b10 N
0@
14
b100000000100000 2
b100000000100000 ]
b100000000100000 \
b100000 F
b1001 V
b0 M
b1100 7
b1100 R
b1001010100100000000100000 (
b1001010100100000000100000 >
b1001010100100000000100000 D
b1000 &
b1000 8
b1000 E
b1000 S
1*
#30000
0*
#35000
b110 C
b110 H
b110 I
b100000000100010 2
b100000000100010 ]
b100000000100010 \
b100010 F
b10000 7
b10000 R
b1001010100100000000100010 (
b1001010100100000000100010 >
b1001010100100000000100010 D
b1100 &
b1100 8
b1100 E
b1100 S
1*
#40000
0*
#45000
b0 C
b0 H
b0 I
b100000000100100 2
b100000000100100 ]
b100000000100100 \
b100100 F
b10100 7
b10100 R
b1001010100100000000100100 (
b1001010100100000000100100 >
b1001010100100000000100100 D
b10000 &
b10000 8
b10000 E
b10000 S
1*
#50000
0*
#55000
b1 C
b1 H
b1 I
b100000000100101 2
b100000000100101 ]
b100000000100101 \
b100101 F
b11000 7
b11000 R
b1001010100100000000100101 (
b1001010100100000000100101 >
b1001010100100000000100101 D
b10100 &
b10100 8
b10100 E
b10100 S
1*
#60000
0*
#65000
b10 C
b10 H
b10 I
b1010 Z
b0 B
b0 G
b0 N
19
03
1@
04
b0 2
b0 ]
b0 \
b0 F
b0 V
b101011 M
b11100 7
b11100 R
b10101100000010100000000000000000 (
b10101100000010100000000000000000 >
b10101100000010100000000000000000 D
b11000 &
b11000 8
b11000 E
b11000 S
1*
#70000
0*
#75000
bx '
bx ;
bx Q
bx 1
bx Y
b1011 Z
09
1<
13
1:
b1011 W
b100011 M
b100000 7
b100000 R
b10001100000010110000000000000000 (
b10001100000010110000000000000000 >
b10001100000010110000000000000000 D
b11100 &
b11100 8
b11100 E
b11100 S
1*
#80000
0*
#85000
b0 '
b0 ;
b0 Q
b110 C
b110 H
b110 I
b1001 Z
b1 B
b1 G
b1 N
1?
0<
03
0:
0@
b10 2
b10 ]
b10 \
b10 F
b1001 W
b1011 V
b100 M
b10x100 7
b10x100 R
b10001011010010000000000000010 (
b10001011010010000000000000010 >
b10001011010010000000000000010 D
b100000 &
b100000 8
b100000 E
b100000 S
1*
#90000
0*
#95000
b10 C
b10 H
b10 I
bx Z
b0 B
b0 G
b0 N
0?
bx 2
bx ]
bx \
bx F
bx W
bx V
bx M
bx 7
bx R
bx (
bx >
bx D
b10x100 &
b10x100 8
b10x100 E
b10x100 S
1*
#100000
0*
#105000
bx &
bx 8
bx E
bx S
1*
